odoo/addons/l10n_th_withholding_tax_cert_form/README.rst
odoo/addons/l10n_th_withholding_tax_cert_form/__init__.py
odoo/addons/l10n_th_withholding_tax_cert_form/__manifest__.py
odoo/addons/l10n_th_withholding_tax_cert_form/data/paper_format.xml
odoo/addons/l10n_th_withholding_tax_cert_form/data/report_data.xml
odoo/addons/l10n_th_withholding_tax_cert_form/i18n/l10n_th_withholding_tax_cert_form.pot
odoo/addons/l10n_th_withholding_tax_cert_form/readme/CONFIGURE.rst
odoo/addons/l10n_th_withholding_tax_cert_form/readme/CONTRIBUTORS.rst
odoo/addons/l10n_th_withholding_tax_cert_form/readme/DESCRIPTION.rst
odoo/addons/l10n_th_withholding_tax_cert_form/readme/INSTALL.rst
odoo/addons/l10n_th_withholding_tax_cert_form/readme/USAGE.rst
odoo/addons/l10n_th_withholding_tax_cert_form/reports/__init__.py
odoo/addons/l10n_th_withholding_tax_cert_form/reports/layout.xml
odoo/addons/l10n_th_withholding_tax_cert_form/reports/withholding_report_pdf.py
odoo/addons/l10n_th_withholding_tax_cert_form/static/description/icon.png
odoo/addons/l10n_th_withholding_tax_cert_form/static/description/index.html
odoo/addons/l10n_th_withholding_tax_cert_form/static/fonts/THSarabunNew Bold.ttf
odoo/addons/l10n_th_withholding_tax_cert_form/static/scss/style_report.scss
odoo/addons/l10n_th_withholding_tax_cert_form/static/src/img/WithholdingCert.jpg
odoo12_addon_l10n_th_withholding_tax_cert_form-12.0.1.0.1.dist-info/METADATA
odoo12_addon_l10n_th_withholding_tax_cert_form-12.0.1.0.1.dist-info/WHEEL
odoo12_addon_l10n_th_withholding_tax_cert_form-12.0.1.0.1.dist-info/top_level.txt
odoo12_addon_l10n_th_withholding_tax_cert_form-12.0.1.0.1.dist-info/RECORD
