Metadata-Version: 2.1
Name: odoo12-addon-l10n-th-withholding-tax-cert-form
Version: 12.0.1.0.1
Summary: Thai Localization - Withholding Tax Certificate Form
Home-page: https://github.com/OCA/l10n-thailand/
Author: Ecosoft,Odoo Community Association (OCA)
Author-email: support@odoo-community.org
License: AGPL-3
Platform: UNKNOWN
Classifier: Programming Language :: Python
Classifier: Framework :: Odoo
Classifier: License :: OSI Approved :: GNU Affero General Public License v3
Requires-Python: >=3.5
Requires-Dist: num2words
Requires-Dist: odoo12-addon-l10n-th-withholding-tax-cert
Requires-Dist: odoo (<12.1dev,>=12.0a)
